py_node_exporter/__init__.py
py_node_exporter/__main__.py
py_node_exporter/py_node_exporter.py
py_node_exporter/collector/__init__.py
py_node_exporter/collector/ccontroller.py
py_node_exporter/collector/collector.py
py_node_exporter/collector/cpu.py
py_node_exporter/collector/diskstats.py
py_node_exporter/collector/filesystem.py
py_node_exporter/collector/loadavg.py
py_node_exporter/collector/meminfo.py
py_node_exporter/collector/namespace.py
py_node_exporter/collector/stat.py
py_node_exporter-1.0.0.dist-info/LICENSE
py_node_exporter-1.0.0.dist-info/METADATA
py_node_exporter-1.0.0.dist-info/WHEEL
py_node_exporter-1.0.0.dist-info/top_level.txt
py_node_exporter-1.0.0.dist-info/RECORD
